large_image_converter/__init__.py
large_image_converter/__main__.py
large_image_converter/format_aperio.py
large_image_converter-1.34.0.dist-info/licenses/LICENSE
large_image_converter-1.34.0.dist-info/METADATA
large_image_converter-1.34.0.dist-info/WHEEL
large_image_converter-1.34.0.dist-info/entry_points.txt
large_image_converter-1.34.0.dist-info/top_level.txt
large_image_converter-1.34.0.dist-info/RECORD
